polyfit/Example_Data.npz
polyfit/__init__.py
polyfit/polyfit.py
polyfit/test.py
polyfit-1.0.dist-info/METADATA
polyfit-1.0.dist-info/WHEEL
polyfit-1.0.dist-info/top_level.txt
polyfit-1.0.dist-info/RECORD
