Metadata-Version: 2.1
Name: polyfit
Version: 1.0
Summary: Constrained polynomial regression
Home-page: https://github.com/dschmitz89/polyfit/
Author: Daniel Schmitz
License: MIT
Platform: UNKNOWN
Requires-Dist: numpy
Requires-Dist: cvxpy
Requires-Dist: scikit-learn
